traffic_light_controller.v
`timescale 1s / 1ms

module traffic_light_controller #(
    parameter GREEN_TIME   = 3'd6,
    parameter YELLOW_TIME  = 3'd1,
    parameter ALL_RED_TIME = 3'd1
)(
    input  wire        clk,
    input  wire        rst,
    output reg  [2:0]  light_A, // East-West:   [2]=Red, [1]=Yellow, [0]=Green
    output reg  [2:0]  light_B  // North-South: [2]=Red, [1]=Yellow, [0]=Green
);

    // Light encoding definitions: 3'b[Red][Yellow][Green]
    localparam RED    = 3'b100;
    localparam YELLOW = 3'b010;
    localparam GREEN  = 3'b001;

    // FSM State Encoding
    localparam [2:0] 
        S0_EW_GREEN  = 3'b000,
        S1_EW_YELLOW = 3'b001,
        S2_ALL_RED_1 = 3'b010,
        S3_NS_GREEN  = 3'b011,
        S4_NS_YELLOW = 3'b100,
        S5_ALL_RED_2 = 3'b101;

    reg [2:0] state;
    reg [2:0] timer;

    // State Transition & Timer Sequential Logic
    always @(posedge clk or posedge rst) begin
        if (rst) begin
            state <= S0_EW_GREEN;
            timer <= 3'd1;
        end else begin
            case (state)
                S0_EW_GREEN: begin
                    if (timer < GREEN_TIME) begin
                        timer <= timer + 1'b1;
                    end else begin
                        state <= S1_EW_YELLOW;
                        timer <= 3'd1;
                    end
                end

                S1_EW_YELLOW: begin
                    if (timer < YELLOW_TIME) begin
                        timer <= timer + 1'b1;
                    end else begin
                        state <= S2_ALL_RED_1;
                        timer <= 3'd1;
                    end
                end

                S2_ALL_RED_1: begin
                    if (timer < ALL_RED_TIME) begin
                        timer <= timer + 1'b1;
                    end else begin
                        state <= S3_NS_GREEN;
                        timer <= 3'd1;
                    end
                end

                S3_NS_GREEN: begin
                    if (timer < GREEN_TIME) begin
                        timer <= timer + 1'b1;
                    end else begin
                        state <= S4_NS_YELLOW;
                        timer <= 3'd1;
                    end
                end

                S4_NS_YELLOW: begin
                    if (timer < YELLOW_TIME) begin
                        timer <= timer + 1'b1;
                    end else begin
                        state <= S5_ALL_RED_2;
                        timer <= 3'd1;
                    end
                end

                S5_ALL_RED_2: begin
                    if (timer < ALL_RED_TIME) begin
                        timer <= timer + 1'b1;
                    end else begin
                        state <= S0_EW_GREEN;
                        timer <= 3'd1;
                    end
                end

                default: begin
                    state <= S0_EW_GREEN;
                    timer <= 3'd1;
                end
            endcase
        end
    end

    // Combinational Output Decoding Logic
    always @(*) begin
        case (state)
            S0_EW_GREEN:  begin light_A = GREEN;  light_B = RED;    end
            S1_EW_YELLOW: begin light_A = YELLOW; light_B = RED;    end
            S2_ALL_RED_1: begin light_A = RED;    light_B = RED;    end
            S3_NS_GREEN:  begin light_A = RED;    light_B = GREEN;  end
            S4_NS_YELLOW: begin light_A = RED;    light_B = YELLOW; end
            S5_ALL_RED_2: begin light_A = RED;    light_B = RED;    end
            default:      begin light_A = RED;    light_B = RED;    end
        endcase
    end

endmodule

traffic_light_controller_tb.v
`timescale 1s / 1ms

module traffic_light_controller_tb;

    reg        clk;
    reg        rst;
    wire [2:0] light_A;
    wire [2:0] light_B;

    // Instantiate Unit Under Test (UUT) with named port connections
    traffic_light_controller #(
        .GREEN_TIME(3'd6),
        .YELLOW_TIME(3'd1),
        .ALL_RED_TIME(3'd1)
    ) uut (
        .clk(clk),
        .rst(rst),
        .light_A(light_A),
        .light_B(light_B)
    );

    // Clock Generator: 1 Hz clock (Period = 1s, #0.5s toggle)
    initial begin
        clk = 1'b0;
        forever #0.5 clk = ~clk;
    end

    // Test Sequence
    initial begin
        // Initialize inputs
        rst = 1'b1;
        #2;

        // Release reset to start FSM
        rst = 1'b0;

        // Run simulation through 2 complete 16-second FSM cycles
        #34;

        $display("Simulation completed successfully.");
        $finish;
    end

    // VCD Waveform Generation for GTKWave
    initial begin
        $dumpfile("dump.vcd");
        $dumpvars(0, traffic_light_controller_tb);
    end

endmodule

dump.vcd
$date
	Sun Aug 30 18:56:48 2026
$end
$version
	Icarus Verilog
$end
$timescale
	1ms
$end
$scope module traffic_light_controller_tb $end
$var wire 3 ! light_B [2:0] $end
$var wire 3 " light_A [2:0] $end
$var reg 1 # clk $end
$var reg 1 $ rst $end
$scope module uut $end
$var wire 1 # clk $end
$var wire 1 $ rst $end
$var reg 3 % light_A [2:0] $end
$var reg 3 & light_B [2:0] $end
$var reg 3 ' state [2:0] $end
$var reg 3 ( timer [2:0] $end
$upscope $end
$upscope $end
$enddefinitions $end
#0
$dumpvars
b1 (
b0 '
b100 &
b1 %
1$
0#
b1 "
b100 !
$end
#500
1#
#1000
0#
#1500
1#
#2000
0#
0$
#2500
b10 (
1#
#3000
0#
#3500
b11 (
1#
#4000
0#
#4500
b100 (
1#
#5000
0#
#5500
b101 (
1#
#6000
0#
#6500
b110 (
1#
#7000
0#
#7500
b10 "
b10 %
b1 (
b1 '
1#
#8000
0#
#8500
b100 "
b100 %
b10 '
1#
#9000
0#
#9500
b1 !
b1 &
b11 '
1#
#10000
0#
#10500
b10 (
1#
#11000
0#
#11500
b11 (
1#
#12000
0#
#12500
b100 (
1#
#13000
0#
#13500
b101 (
1#
#14000
0#
#14500
b110 (
1#
#15000
0#
#15500
b10 !
b10 &
b1 (
b100 '
1#
#16000
0#
#16500
b100 !
b100 &
b101 '
1#
#17000
0#
#17500
b1 "
b1 %
b0 '
1#
#18000
0#
#18500
b10 (
1#
#19000
0#
#19500
b11 (
1#
#20000
0#
#20500
b100 (
1#
#21000
0#
#21500
b101 (
1#
#22000
0#
#22500
b110 (
1#
#23000
0#
#23500
b10 "
b10 %
b1 (
b1 '
1#
#24000
0#
#24500
b100 "
b100 %
b10 '
1#
#25000
0#
#25500
b1 !
b1 &
b11 '
1#
#26000
0#
#26500
b10 (
1#
#27000
0#
#27500
b11 (
1#
#28000
0#
#28500
b100 (
1#
#29000
0#
#29500
b101 (
1#
#30000
0#
#30500
b110 (
1#
#31000
0#
#31500
b10 !
b10 &
b1 (
b100 '
1#
#32000
0#
#32500
b100 !
b100 &
b101 '
1#
#33000
0#
#33500
b1 "
b1 %
b0 '
1#
#34000
0#
#34500
b10 (
1#
#35000
0#
#35500
b11 (
1#
